birger_minimal/minimal.py
birger_minimal2-0.0.2.dist-info/METADATA
birger_minimal2-0.0.2.dist-info/WHEEL
birger_minimal2-0.0.2.dist-info/top_level.txt
birger_minimal2-0.0.2.dist-info/RECORD
