Metadata-Version: 2.4
Name: birger-minimal2
Version: 0.0.2
Requires-Dist: apis-core-rdf>=0.48.0
